icotronic/__init__.py
icotronic/can/__init__.py
icotronic/can/adc.py
icotronic/can/calibration.py
icotronic/can/connection.py
icotronic/can/constants.py
icotronic/can/dataloss.py
icotronic/can/error.py
icotronic/can/listener.py
icotronic/can/node/basic.py
icotronic/can/node/eeprom/__init__.py
icotronic/can/node/eeprom/basic.py
icotronic/can/node/eeprom/node.py
icotronic/can/node/eeprom/sensor.py
icotronic/can/node/eeprom/status.py
icotronic/can/node/eeprom/sth.py
icotronic/can/node/id.py
icotronic/can/node/sensor.py
icotronic/can/node/spu.py
icotronic/can/node/sth.py
icotronic/can/node/stu.py
icotronic/can/protocol/blocks.py
icotronic/can/protocol/command.py
icotronic/can/protocol/identifier.py
icotronic/can/protocol/message.py
icotronic/can/sensor.py
icotronic/can/status.py
icotronic/can/streaming/__init__.py
icotronic/can/streaming/buffer.py
icotronic/can/streaming/config.py
icotronic/can/streaming/data.py
icotronic/can/streaming/error.py
icotronic/can/streaming/format.py
icotronic/cmdline/__init__.py
icotronic/cmdline/parse.py
icotronic/config/__init__.py
icotronic/config/config.py
icotronic/config/config.yaml
icotronic/config/user.yaml
icotronic/examples/concurrent_access.py
icotronic/examples/read_data.py
icotronic/examples/sth_name.py
icotronic/examples/store_data.py
icotronic/measurement/__init__.py
icotronic/measurement/acceleration.py
icotronic/measurement/constants.py
icotronic/measurement/data.py
icotronic/measurement/sensor.py
icotronic/measurement/storage.py
icotronic/measurement/voltage.py
icotronic/scripts/__init__.py
icotronic/scripts/icon.py
icotronic/test/misc.py
icotronic/utility/__init__.py
icotronic/utility/data.py
icotronic/utility/log.py
icotronic/utility/naming.py
icotronic/utility/performance.py
icotronic/utility/types.py
icotronic-6.2.0.dist-info/METADATA
icotronic-6.2.0.dist-info/WHEEL
icotronic-6.2.0.dist-info/entry_points.txt
icotronic-6.2.0.dist-info/RECORD
