Metadata-Version: 2.4
Name: icotronic
Version: 6.2.0
Summary: Control software for sensory tool holders (STH), sensor milling heads (SMH) and stationary transceiver units (STU)
Keywords: smart-tool,smh,stu,sth,tool-holder
Author: Clemens Burgstaller
Author-email: burgstaller@ift.at
Requires-Python: >=3.12,<4
Classifier: Development Status :: 3 - Alpha
Classifier: Natural Language :: English
Classifier: Operating System :: MacOS
Classifier: Operating System :: POSIX :: Linux
Classifier: Operating System :: Microsoft :: Windows :: Windows 11
Classifier: Programming Language :: Python
Provides-Extra: dev
Requires-Dist: Flake8-pyproject (>=1.2.3) ; extra == "dev"
Requires-Dist: bidict (>=0.22.1,<2)
Requires-Dist: blosc2 (>=2.3.0)
Requires-Dist: coverage (>=7.8.2) ; extra == "dev"
Requires-Dist: dynaconf (>=3.1.12,<4)
Requires-Dist: icolyzer (>=1.5.0) ; extra == "dev"
Requires-Dist: mypy ; extra == "dev"
Requires-Dist: netaddr (>=0.8.0,<2)
Requires-Dist: platformdirs (>=3.5.0,<5)
Requires-Dist: prysk[pytest-plugin] (>=0.15.1) ; extra == "dev"
Requires-Dist: pydoclint[flake8] (>=0.6.6) ; extra == "dev"
Requires-Dist: pylint (>=3.3.1) ; extra == "dev"
Requires-Dist: pytest-asyncio ; extra == "dev"
Requires-Dist: pytest-rerunfailures (>=16.1) ; extra == "dev"
Requires-Dist: pytest-sphinx ; extra == "dev"
Requires-Dist: pytest-sugar (>=1.1.1) ; extra == "dev"
Requires-Dist: python-can[pcan] (>=4,<5)
Requires-Dist: semantic_version (>=2.10,<3)
Requires-Dist: sphinx (>=9,<10) ; extra == "dev"
Requires-Dist: sphinx-autodoc-typehints (>=3) ; extra == "dev"
Requires-Dist: sphinx_rtd_theme (>=3.1.0rc1) ; extra == "dev"
Requires-Dist: sphinx_toggleprompt (>=0.6.0) ; extra == "dev"
Requires-Dist: tables (>=3.10.1,<4)
Requires-Dist: toml ; extra == "dev"
Requires-Dist: tqdm (>=4.65,<5)
Requires-Dist: universal-startfile (>=0.4)
Project-URL: Documentation, https://mytoolit.github.io/ICOtronic/
Project-URL: Source, https://github.com/mytoolit/ICOtronic/
